bridge/__init__.py
bridge/display/__init__.py
bridge/display/basic.py
bridge/display/display_engine.py
bridge/display/text.py
bridge/display/vision.py
bridge/engines/__init__.py
bridge/engines/pytorch.py
bridge/primitives/__init__.py
bridge/primitives/dataset/__init__.py
bridge/primitives/dataset/dataset.py
bridge/primitives/dataset/sample_api.py
bridge/primitives/dataset/singular_dataset.py
bridge/primitives/dataset/table_api.py
bridge/primitives/element/__init__.py
bridge/primitives/element/data/__init__.py
bridge/primitives/element/data/cache_mechanism.py
bridge/primitives/element/data/category_registry.py
bridge/primitives/element/data/data_io.py
bridge/primitives/element/data/load_mechanism.py
bridge/primitives/element/data/uri_components.py
bridge/primitives/element/element.py
bridge/primitives/element/element_data_type.py
bridge/primitives/sample/__init__.py
bridge/primitives/sample/sample.py
bridge/primitives/sample/singular_sample.py
bridge/primitives/sample/transform/__init__.py
bridge/primitives/sample/transform/sample_transform.py
bridge/primitives/sample/transform/vision.py
bridge/primitives/types.py
bridge/primitives/utils.py
bridge/providers/__init__.py
bridge/providers/dataset_provider.py
bridge/providers/text.py
bridge/providers/vision.py
bridge/utils/__init__.py
bridge/utils/constants.py
bridge/utils/data_objects.py
bridge/utils/download_and_extract_archive.py
bridge/utils/helper.py
bridge/utils/optional_import.py
bridge/utils/pmap.py
bridge_ds-0.1.1.dist-info/WHEEL
bridge_ds-0.1.1.dist-info/METADATA
bridge_ds-0.1.1.dist-info/RECORD
