Metadata-Version: 2.3
Name: bridge-ds
Version: 0.1.1
Summary: A Bridge to Datasets!
Requires-Dist: pandas
Requires-Dist: numpy
Requires-Dist: tqdm
Requires-Dist: scikit-image ; extra == 'vision'
Requires-Dist: pillow ; extra == 'vision'
Requires-Dist: holoviews ; extra == 'vision'
Requires-Dist: panel ; extra == 'vision'
Requires-Dist: hvplot ; extra == 'vision'
Requires-Dist: tabulate ; extra == 'vision'
Requires-Dist: jupyter-bokeh ; extra == 'vision'
Requires-Python: >=3.11
Provides-Extra: vision
